pylib_openblas/__init__.py
pylib_openblas/placeholder.cpython-36m-darwin.so
pylib_openblas/include/openblas/cblas.h
pylib_openblas/include/openblas/openblas_config.h
pylib_openblas/lib/libopenblas.a
pylib_openblas/lib/pkgconfig/openblas.pc
pylib_openblas/share/cmake/OpenBLAS/OpenBLASConfig.cmake
pylib_openblas/share/cmake/OpenBLAS/OpenBLASConfigVersion.cmake
pylib_openblas/share/cmake/OpenBLAS/OpenBLASTargets-release.cmake
pylib_openblas/share/cmake/OpenBLAS/OpenBLASTargets.cmake
pylib_openblas-0.0.2.dist-info/METADATA
pylib_openblas-0.0.2.dist-info/WHEEL
pylib_openblas-0.0.2.dist-info/top_level.txt
pylib_openblas-0.0.2.dist-info/RECORD
